odoo/addons/stock_request_picking_type/README.rst
odoo/addons/stock_request_picking_type/__init__.py
odoo/addons/stock_request_picking_type/__manifest__.py
odoo/addons/stock_request_picking_type/data/stock_picking_type.xml
odoo/addons/stock_request_picking_type/i18n/es.po
odoo/addons/stock_request_picking_type/i18n/pt_BR.po
odoo/addons/stock_request_picking_type/i18n/stock_request_picking_type.pot
odoo/addons/stock_request_picking_type/i18n/zh_CN.po
odoo/addons/stock_request_picking_type/migrations/12.0.2.0.0/post-migration.py
odoo/addons/stock_request_picking_type/models/__init__.py
odoo/addons/stock_request_picking_type/models/stock_picking_type.py
odoo/addons/stock_request_picking_type/models/stock_request_order.py
odoo/addons/stock_request_picking_type/readme/CONTRIBUTORS.rst
odoo/addons/stock_request_picking_type/readme/DESCRIPTION.rst
odoo/addons/stock_request_picking_type/readme/USAGE.rst
odoo/addons/stock_request_picking_type/static/description/icon.png
odoo/addons/stock_request_picking_type/static/description/index.html
odoo/addons/stock_request_picking_type/views/stock_picking_views.xml
odoo/addons/stock_request_picking_type/views/stock_request_order_views.xml
odoo12_addon_stock_request_picking_type-12.0.2.1.2.dist-info/METADATA
odoo12_addon_stock_request_picking_type-12.0.2.1.2.dist-info/WHEEL
odoo12_addon_stock_request_picking_type-12.0.2.1.2.dist-info/top_level.txt
odoo12_addon_stock_request_picking_type-12.0.2.1.2.dist-info/RECORD
